Workbook

Sheet 🕐 Rutina Diaria
A1: 🕐 RUTINA DIARIA — Modelo Reversal Scanner v9 · Inicio: Lunes 21 Abr 2026
A2: 4 momentos clave del día · Ejecutar en orden · Cada uno tiene un objetivo específico
A3: Hora | B3: Momento | C3: Qué hacer | D3: Tab en v9 | E3: Decisión
A4: 07:00 AM · 🌅 OPORTUNIDADES DEL DÍA · Antes de abrir el mercado
A5: 07:00 AM | B5: ✅ Abrir v9 | C5: Revisar VIX + S&P500 + Señal del modelo en el header | D5: ⚡ Swing Activo 🔥 Entrar hoy 📡 Detectadas M1 | E5: ¿Entro hoy? ¿A qué precio? ¿Con cuánto capital?
B6: ✅ Escanear Swing Activo | C6: ¿Hay señales con fase ENTRADA VÁLIDA o ENTRAR HOY?
B7: ✅ Escanear Entrar hoy | C7: ¿Hay M3 confirmado con catalizador activo?
B8: ✅ Escanear Detectadas M1 | C8: ¿Hay acciones nuevas en corrección para watchlist?
B9: ✅ Revisar Prob NBIS | C9: Priorizar acciones con Prob NBIS > 60%
B10: 📝 Registrar en tracker | C10: Anotar señales en hoja Paper Trading antes de abrir
A12: 10:30 AM · ⚡ ACTUALIZAR POSICIONES · 1 hora después de apertura
A13: 10:30 AM | B13: ✅ Abrir Mis Posiciones | C13: Verificar PnL live de cada posición | D13: 💼 Mis Posiciones ⚡ Swing Activo | E13: ¿Completo posición? ¿Ajusto stop? ¿Entro tarde?
B14: ✅ Revisar Pre-Market vs apertura | C14: ¿El movimiento confirmó o revirtió?
B15: ✅ Evaluar entradas pendientes | C15: Si tenías orden de 50% → ¿confirma para completar al 100%?
B16: ✅ Verificar volumen apertura | C16: Vol > 150% del promedio = señal válida
B17: ✅ Actualizar stops | C17: Ajustar stop a precio de entrada si ya ganó +5%
B18: 📝 Revisar noticias | C18: ¿Algún catalizador nuevo en el sidebar?
A20: 01:00 PM · 👀 REVISAR STOPS · Mitad de sesión
A21: 01:00 PM | B21: ✅ Abrir Mis Posiciones | C21: Verificar si alguna posición está cerca del stop | D21: 💼 Mis Posiciones 🔗 Sympathy ⚡ Swing Activo | E21: ¿Ejecuto stop? ¿Vendo Tramo 1? ¿Nuevo swing tarde?
B22: ✅ Revisar posiciones en pérdida | C22: ¿Alguna bajó más del -3%? Preparar salida
B23: ✅ Confirmar targets alcanzados | C23: ¿Alguna llegó a Target 1 (+8%)? Ejecutar venta 60%
B24: ✅ Revisar Sympathy | C24: ¿Hay nuevas acciones arrastradas por el sector?
B25: ✅ Escanear Swing si no lo hiciste | C25: Segunda oportunidad si el mercado giró en la mañana
B26: 📝 Registrar movimientos en tracker | C26: Anotar precio día 5 en paper trading si corresponde
A28: 03:45 PM · 🏁 DECISIÓN FINAL DEL DÍA · 15 min antes del cierre
A29: 03:45 PM | B29: ✅ Revisar posiciones abiertas | C29: ¿Alguna en zona peligrosa para el cierre? | D29: 💼 Mis Posiciones 📊 Vista completa | E29: ¿Cierro posición? ¿Mantengo overnight? ¿Qué vigilar mañana?
B30: ✅ Ejecutar salidas pendientes | C30: Si el stop se activó durante el día → salir antes del cierre
B31: ✅ Confirmar Target 1 si llegó | C31: No dejar para mañana: vender 60% si llegó +8%
B32: ✅ Revisar VIX final del día | C32: VIX subió mucho = precaución mañana
B33: ✅ Registrar todo en tracker | C33: Actualizar Paper Trading con precios del cierre
B34: 📝 Preparar lista de mañana | C34: ¿Qué acciones de Detectadas M1 vigilar mañana?
A36: ⚡ REGLAS DE ORO DEL MODELO
A37: 🛑 Stop -5% | B37: Si la acción baja -5% desde tu entrada, sales ESE DÍA sin excepción ni debate
A38: 📅 Día 10 | B38: Si llevas 10 días en el swing y no llegó al target, vendes TODO ese día
A39: ⚡ 50% primero | B39: En Entrada Válida: entrar con 50%. Si mañana confirma volumen → completar al 100%
A40: 🎯 Tramo 1 siempre | B40: Cuando llegue a +8%, vender 60% para asegurar ganancia. SIEMPRE.
A41: 📊 Registrar todo | B41: Si no está en el tracker, no existe. Cada señal debe quedar registrada.
A42: 🔄 Paper trading 2 semanas | B42: Antes de operar con capital real, completar las 2 semanas de paper trading

Sheet 📋 Guía Rápida
A1: 📋 GUÍA RÁPIDA — Cómo usar el tracker del modelo v9
A3: LOS 3 TABS DEL MODELO — y cuándo registrar
A4: 📡 Detectadas M1 | B4: La acción está cayendo | C4: Solo agregar a watchlist. NO registrar en paper trading aún. Anotar en columna 'Notas' para seguimiento.
A5: ⚡ Swing Activo | B5: La acción ya rebotó 2-3 días | C5: SÍ registrar en paper trading. Anota fecha, ticker, fase (Temprana/Válida/Hoy), precio y stop.
A6: 🔥 Entrar hoy | B6: M3 confirmado con catalizador | C6: SÍ registrar en paper trading. Señal más fuerte del modelo. Anota todo con detalle.
A7: LAS 3 FASES DEL SWING
A8: 👀 TEMPRANA | B8: M1→M2: Solo 2 días subiendo | C8: NO entrar. Anotar en Notas para seguimiento. Si mañana confirma → registrar como Entrada Válida.
A9: ⚡ ENTRADA VÁLIDA | B9: M2: Rebote confirmado | C9: Entrar 50% del tamaño. Registrar precio entrada. Si mañana sube con vol → completar al 100%.
A10: 🔥 ENTRAR HOY | B10: M3: 3+ días + volumen alto | C10: Entrar 100% del tamaño. Registrar con todos los datos. Es la señal más completa del swing.
A11: QUÉ REGISTRAR AL ENTRAR
A12: Fecha señal | B12: Fecha en que el modelo la detectó | C12: Importante para calcular días en posición y comparar con SPY del mismo período.
A13: Tab señal | B13: Tab donde apareció la señal | C13: Escribir exactamente: 'Swing Activo', 'Entrar hoy' o 'Detectadas M1'.
A14: Fase | B14: Fase de entrada detectada | C14: TEMPRANA · ENTRADA VÁLIDA · ENTRAR HOY · M3 CONFIRMADO
A15: VIX entrada | B15: VIX del día que entras | C15: Lo ves en el header del dashboard. Importante para calibrar si el modelo funciona mejor con VIX alto.
A16: RSI entrada | B16: RSI de la acción al entrar | C16: Lo ves en la tarjeta del scanner. Valida que los filtros del modelo son correctos.
A17: Volumen % | B17: Volumen vs promedio del día | C17: 🟢 Alto >150% · 🟡 Normal 100-150% · 🔴 Bajo <100%
A18: Prob NBIS % | B18: Probabilidad de seguir patrón NBIS | C18: Aparece en cada tarjeta. Registrar para correlacionar con resultado final.
A19: QUÉ REGISTRAR AL SALIR
A20: Precio día 5 | B20: Precio exacto al quinto día hábil | C20: Registrar aunque no hayas salido. Para medir si el modelo acierta en el timing.
A21: Precio día 10 | B21: Precio exacto al décimo día hábil | C21: Salida obligatoria del swing. Si no llegó al target, igual sales.
A22: ¿Llegó a Target 1? | B22: ¿Alcanzó el +8%? | C22: Sí/No. Si Sí → vendiste 60% en ese punto.
A23: ¿Llegó a Target 2? | B23: ¿Alcanzó el +12%? | C23: Sí/No. Si Sí → vendiste el runner 40%.
A24: ¿Activó stop? | B24: ¿Bajó más del -5%? | C24: Sí/No. Si Sí → salida total ese día sin excepción.
A25: Resultado final % | B25: Ganancia o pérdida real | C25: Calcular sobre el capital total comprometido, no solo la parte vendida.
A26: SPY mismo período | B26: Cuánto subió SPY en los mismos días | C26: Buscar en Google: SPY precio día entrada vs día salida. Clave para medir alpha del modelo.
A27: ¿Modelo correcto? | B27: ¿La señal fue acertada? | C27: Sí = ganó dinero o evitó pérdida. No = perdió. Neutral = resultado mixto.

Sheet ⚡ Paper Trading
A1: ⚡ PAPER TRADING — Señales modelo v9 · 21 Abr 2026 — 02 May 2026
A2: Registra SOLO señales de ⚡ Swing Activo y 🔥 Entrar hoy. Para 📡 Detectadas M1 usar columna Notas.
A3: IDENTIFICACIÓN | E3: CONTEXTO MERCADO AL ENTRAR | I3: PRECIOS | M3: SEGUIMIENTO | R3: RESULTADO | V3: ANÁLISIS
A4: Fecha Señal | B4: Ticker | C4: Tab Señal | D4: Fase detectada | E4: VIX entrada | F4: RSI entrada | G4: Vol % | H4: Prob NBIS % | I4: Precio entrada | J4: Stop -5% | K4: Target 1 +8% | L4: Target 2 +12% | M4: Precio día 5 | N4: ¿T1 alcanzado? | O4: Precio día 10 | P4: ¿T2 alcanzado? | Q4: ¿Stop activado? | R4: Resultado % | S4: SPY mismo período | T4: Alpha vs SPY | U4: ¿Modelo correcto? | V4: Días en posición | W4: Notas
J5: =IF(I5<>"",I5*0.95,"") | K5: =IF(I5<>"",I5*1.08,"") | L5: =IF(I5<>"",I5*1.12,"") | R5: =IF(AND(I5<>"",O5<>""),( O5-I5)/I5,"") | T5: =IF(AND(R5<>"",S5<>""),R5-S5,"") | V5: =IF(A5<>"",TODAY()-A5,"")
J6: =IF(I6<>"",I6*0.95,"") | K6: =IF(I6<>"",I6*1.08,"") | L6: =IF(I6<>"",I6*1.12,"") | R6: =IF(AND(I6<>"",O6<>""),( O6-I6)/I6,"") | T6: =IF(AND(R6<>"",S6<>""),R6-S6,"") | V6: =IF(A6<>"",TODAY()-A6,"")
J7: =IF(I7<>"",I7*0.95,"") | K7: =IF(I7<>"",I7*1.08,"") | L7: =IF(I7<>"",I7*1.12,"") | R7: =IF(AND(I7<>"",O7<>""),( O7-I7)/I7,"") | T7: =IF(AND(R7<>"",S7<>""),R7-S7,"") | V7: =IF(A7<>"",TODAY()-A7,"")
J8: =IF(I8<>"",I8*0.95,"") | K8: =IF(I8<>"",I8*1.08,"") | L8: =IF(I8<>"",I8*1.12,"") | R8: =IF(AND(I8<>"",O8<>""),( O8-I8)/I8,"") | T8: =IF(AND(R8<>"",S8<>""),R8-S8,"") | V8: =IF(A8<>"",TODAY()-A8,"")
J9: =IF(I9<>"",I9*0.95,"") | K9: =IF(I9<>"",I9*1.08,"") | L9: =IF(I9<>"",I9*1.12,"") | R9: =IF(AND(I9<>"",O9<>""),( O9-I9)/I9,"") | T9: =IF(AND(R9<>"",S9<>""),R9-S9,"") | V9: =IF(A9<>"",TODAY()-A9,"")
J10: =IF(I10<>"",I10*0.95,"") | K10: =IF(I10<>"",I10*1.08,"") | L10: =IF(I10<>"",I10*1.12,"") | R10: =IF(AND(I10<>"",O10<>""),( O10-I10)/I10,"") | T10: =IF(AND(R10<>"",S10<>""),R10-S10,"") | V10: =IF(A10<>"",TODAY()-A10,"")
J11: =IF(I11<>"",I11*0.95,"") | K11: =IF(I11<>"",I11*1.08,"") | L11: =IF(I11<>"",I11*1.12,"") | R11: =IF(AND(I11<>"",O11<>""),( O11-I11)/I11,"") | T11: =IF(AND(R11<>"",S11<>""),R11-S11,"") | V11: =IF(A11<>"",TODAY()-A11,"")
J12: =IF(I12<>"",I12*0.95,"") | K12: =IF(I12<>"",I12*1.08,"") | L12: =IF(I12<>"",I12*1.12,"") | R12: =IF(AND(I12<>"",O12<>""),( O12-I12)/I12,"") | T12: =IF(AND(R12<>"",S12<>""),R12-S12,"") | V12: =IF(A12<>"",TODAY()-A12,"")
J13: =IF(I13<>"",I13*0.95,"") | K13: =IF(I13<>"",I13*1.08,"") | L13: =IF(I13<>"",I13*1.12,"") | R13: =IF(AND(I13<>"",O13<>""),( O13-I13)/I13,"") | T13: =IF(AND(R13<>"",S13<>""),R13-S13,"") | V13: =IF(A13<>"",TODAY()-A13,"")
J14: =IF(I14<>"",I14*0.95,"") | K14: =IF(I14<>"",I14*1.08,"") | L14: =IF(I14<>"",I14*1.12,"") | R14: =IF(AND(I14<>"",O14<>""),( O14-I14)/I14,"") | T14: =IF(AND(R14<>"",S14<>""),R14-S14,"") | V14: =IF(A14<>"",TODAY()-A14,"")
J15: =IF(I15<>"",I15*0.95,"") | K15: =IF(I15<>"",I15*1.08,"") | L15: =IF(I15<>"",I15*1.12,"") | R15: =IF(AND(I15<>"",O15<>""),( O15-I15)/I15,"") | T15: =IF(AND(R15<>"",S15<>""),R15-S15,"") | V15: =IF(A15<>"",TODAY()-A15,"")
J16: =IF(I16<>"",I16*0.95,"") | K16: =IF(I16<>"",I16*1.08,"") | L16: =IF(I16<>"",I16*1.12,"") | R16: =IF(AND(I16<>"",O16<>""),( O16-I16)/I16,"") | T16: =IF(AND(R16<>"",S16<>""),R16-S16,"") | V16: =IF(A16<>"",TODAY()-A16,"")
... J54: =IF(I54<>"",I54*0.95,"") | K54: =IF(I54<>"",I54*1.08,"") | L54: =IF(I54<>"",I54*1.12,"") | R54: =IF(AND(I54<>"",O54<>""),( O54-I54)/I54,"") | T54: =IF(AND(R54<>"",S54<>""),R54-S54,"") | V54: =IF(A54<>"",TODAY()-A54,"")

Sheet 📊 Historial Real
A1: 📊 HISTORIAL — Operaciones reales ejecutadas + oportunidades perdidas
A2: Incluye: tus operaciones + operaciones de tu señora + oportunidades que viste y no entraste
A3: Ticker | B3: Nombre | C3: Quién | D3: Tipo (Ejecutada/No entré) | E3: Tab Señal | F3: VIX entrada | G3: RSI entrada | H3: Fecha Entrada | I3: Precio Entrada | J3: Cantidad | K3: Capital $ | L3: Fecha Salida | M3: Precio Salida | N3: P&L $ | O3: P&L % | P3: SPY mismo período | Q3: Alpha vs SPY | R3: Prob NBIS al entrar | S3: ¿Modelo correcto?
A4: OPEN | B4: Opendoor | C4: Yo | D4: Ejecutada | E4: — | F4: 18 | G4: 32 | H4: 2025-08-15 | I4: 4.54 | J4: 100 | K4: =I4*J4 -> 454 | L4: 2025-11-20 | M4: 8 | N4: =(M4-I4)*J4 -> 346 | O4: =IF(AND(I4>0,M4>0),(M4-I4)/I4,"") -> 0.76211454 | Q4: =IF(AND(O4<>"",P4<>""),O4-P4,"")
A5: NKE | B5: Nike | C5: Yo | D5: Ejecutada | E5: — | F5: 16 | G5: 48 | H5: 2022-07-01 | I5: 131.96 | J5: 2 | K5: =I5*J5 -> 263.92 | L5: Abierta | M5: 45.44 | N5: =(M5-I5)*J5 -> -173.04 | O5: =IF(AND(I5>0,M5>0),(M5-I5)/I5,"") -> -0.65565323 | Q5: =IF(AND(O5<>"",P5<>""),O5-P5,"")
A6: CNC | B6: Centene | C6: Yo | D6: Ejecutada | E6: — | F6: 22 | G6: 45 | H6: 2025-10-07 | I6: 38.22 | J6: 9 | K6: =I6*J6 -> 343.98 | L6: Abierta | M6: 27 | N6: =(M6-I6)*J6 -> -100.98 | O6: =IF(AND(I6>0,M6>0),(M6-I6)/I6,"") -> -0.29356358 | Q6: =IF(AND(O6<>"",P6<>""),O6-P6,"")
A7: CLOV | B7: Clover | C7: Yo | D7: Ejecutada | E7: — | F7: 21 | G7: 42 | H7: 2025-10-01 | I7: 2.66 | J7: 117 | K7: =I7*J7 -> 311.22 | L7: Abierta | M7: 1.92 | N7: =(M7-I7)*J7 -> -86.58 | O7: =IF(AND(I7>0,M7>0),(M7-I7)/I7,"") -> -0.27819549 | Q7: =IF(AND(O7<>"",P7<>""),O7-P7,"")
A8: NBIS | B8: Nebius | C8: Yo | D8: Ejecutada | E8: — | F8: 18 | G8: 38 | H8: 2026-04-09 | I8: 129.9 | J8: 3 | K8: =I8*J8 -> 389.7 | L8: Abierta | M8: 156.89 | N8: =(M8-I8)*J8 -> 80.97 | O8: =IF(AND(I8>0,M8>0),(M8-I8)/I8,"") -> 0.20777521 | Q8: =IF(AND(O8<>"",P8<>""),O8-P8,"")
A9: MRNA | B9: Moderna | C9: Yo | D9: Ejecutada | E9: — | F9: 24 | G9: 32 | H9: 2026-02-17 | I9: 42.58 | J9: 15 | K9: =I9*J9 -> 638.7 | L9: Abierta | M9: 54.03 | N9: =(M9-I9)*J9 -> 171.75 | O9: =IF(AND(I9>0,M9>0),(M9-I9)/I9,"") -> 0.26890559 | Q9: =IF(AND(O9<>"",P9<>""),O9-P9,"")
A10: TAN | B10: Invesco Solar | C10: Yo | D10: Ejecutada | E10: — | F10: 20 | G10: 45 | H10: 2026-02-17 | I10: 58.29 | J10: 11 | K10: =I10*J10 -> 641.19 | L10: Abierta | M10: 55.1 | N10: =(M10-I10)*J10 -> -35.09 | O10: =IF(AND(I10>0,M10>0),(M10-I10)/I10,"") -> -0.054726368 | Q10: =IF(AND(O10<>"",P10<>""),O10-P10,"")
A11: NVDA | B11: NVIDIA | C11: Yo | D11: Ejecutada | E11: — | F11: 19 | G11: 38 | H11: 2025-10-02 | I11: 189.47 | J11: 2 | K11: =I11*J11 -> 378.94 | L11: Abierta | M11: 197.57 | N11: =(M11-I11)*J11 -> 16.2 | O11: =IF(AND(I11>0,M11>0),(M11-I11)/I11,"") -> 0.042750831 | Q11: =IF(AND(O11<>"",P11<>""),O11-P11,"")
A12: CROX | B12: Crocs | C12: Yo | D12: Ejecutada | E12: — | F12: 21 | G12: 40 | H12: 2025-10-07 | I12: 78.72 | J12: 4 | K12: =I12*J12 -> 314.88 | L12: Abierta | M12: 100 | N12: =(M12-I12)*J12 -> 85.12 | O12: =IF(AND(I12>0,M12>0),(M12-I12)/I12,"") -> 0.2703252 | Q12: =IF(AND(O12<>"",P12<>""),O12-P12,"")
A13: APLD | B13: Applied Digital | C13: Yo | D13: Ejecutada | E13: — | F13: 18 | G13: 35 | H13: 2026-04-09 | I13: 26.64 | J13: 13 | K13: =I13*J13 -> 346.32 | L13: Abierta | M13: 29.54 | N13: =(M13-I13)*J13 -> 37.7 | O13: =IF(AND(I13>0,M13>0),(M13-I13)/I13,"") -> 0.10885886 | Q13: =IF(AND(O13<>"",P13<>""),O13-P13,"")
A14: ASTS | B14: AST SpaceMobile | C14: Yo | D14: Ejecutada | E14: — | F14: 22 | G14: 42 | H14: 2025-10-29 | I14: 79.21 | J14: 2 | K14: =I14*J14 -> 158.42 | L14: Abierta | M14: 86.83 | N14: =(M14-I14)*J14 -> 15.24 | O14: =IF(AND(I14>0,M14>0),(M14-I14)/I14,"") -> 0.096199975 | Q14: =IF(AND(O14<>"",P14<>""),O14-P14,"")
A15: ACN | B15: Accenture | C15: Yo | D15: No entré | E15: Radar | F15: 35 | G15: 30 | H15: 2026-04-07 | I15: 177 | J15: 0 | K15: 0 | L15: — | M15: 193.75 | N15: — | O15: =IF(AND(I15>0,M15>0),(M15-I15)/I15,"") -> 0.094632768 | Q15: =IF(AND(O15<>"",P15<>""),O15-P15,"")
A16: STAA | B16: STAAR Surgical | C16: Yo | D16: No entré | E16: Radar | F16: 28 | G16: 28 | H16: 2026-02-01 | I16: 15.59 | J16: 0 | K16: 0 | L16: — | M16: 25.02 | N16: — | O16: =IF(AND(I16>0,M16>0),(M16-I16)/I16,"") -> 0.60487492 | Q16: =IF(AND(O16<>"",P16<>""),O16-P16,"")

Sheet 📈 Métricas
A1: 📈 MÉTRICAS DEL MODELO v9 — Calculadas automáticamente
A3: PAPER TRADING — Señales v9 · 21 Abr — 02 May 2026 (2 semanas)
A4: Total señales registradas | B4: =COUNTA('⚡ Paper Trading'!B5:B54) -> 0 | C4: Meta: mínimo 10 señales
A5: Señales correctas (resultado > 0) | B5: =COUNTIF('⚡ Paper Trading'!R5:R54,">0") -> 0 | C5: —
A6: Tasa de acierto Paper Trading | B6: =IFERROR(COUNTIF('⚡ Paper Trading'!R5:R54,">0")/COUNTA('⚡ Paper Trading'!B5:B54),0) -> 0 | C6: Objetivo > 55%
A7: Ganancia promedio ganadores | B7: =IFERROR(AVERAGEIF('⚡ Paper Trading'!R5:R54,">0",'⚡ Paper Trading'!R5:R54),0) -> 0 | C7: Objetivo > 8%
A8: Pérdida promedio perdedores | B8: =IFERROR(AVERAGEIF('⚡ Paper Trading'!R5:R54,"<0",'⚡ Paper Trading'!R5:R54),0) -> 0 | C8: Objetivo > -5%
A9: Alpha promedio vs SPY | B9: =IFERROR(AVERAGE('⚡ Paper Trading'!T5:T54),0) -> 0 | C9: Objetivo > 0%
A10: Señales Swing Activo | B10: =COUNTIF('⚡ Paper Trading'!C5:C54,"Swing Activo") -> 0 | C10: —
A11: Señales Entrar hoy | B11: =COUNTIF('⚡ Paper Trading'!C5:C54,"Entrar hoy") -> 0 | C11: —
A13: HISTORIAL REAL — Operaciones ejecutadas
A14: Total operaciones ejecutadas | B14: =COUNTIF('📊 Historial Real'!D4:D50,"Ejecutada") -> 11 | C14: Historial total
A15: Operaciones ganadoras | B15: =COUNTIFS('📊 Historial Real'!D4:D50,"Ejecutada",'📊 Historial Real'!O4:O50,">0") -> 7 | C15: —
A16: Tasa de acierto real | B16: =IFERROR(COUNTIFS('📊 Historial Real'!D4:D50,"Ejecutada",'📊 Historial Real'!O4:O50,">0")/COUNTIF('📊 Historial Real'!D4:D50,"Ejecutada"),0) -> 0.63636364 | C16: Objetivo > 55%
A17: Ganancia promedio ganadores | B17: =IFERROR(AVERAGEIFS('📊 Historial Real'!O4:O50,'📊 Historial Real'!D4:D50,"Ejecutada",'📊 Historial Real'!O4:O50,">0"),0) -> 0.25099003 | C17: Objetivo > 20%
A18: Pérdida promedio perdedores | B18: =IFERROR(AVERAGEIFS('📊 Historial Real'!O4:O50,'📊 Historial Real'!D4:D50,"Ejecutada",'📊 Historial Real'!O4:O50,"<0"),0) -> -0.32053467 | C18: Objetivo > -10%
A19: Alpha promedio vs SPY | B19: =IFERROR(AVERAGE('📊 Historial Real'!Q4:Q50),0) -> 0 | C19: Objetivo > 0%
A20: Oportunidades perdidas detectadas | B20: =COUNTIF('📊 Historial Real'!D4:D50,"No entré") -> 2 | C20: Para calibrar
